dtcc_io/__init__.py
dtcc_io/city.py
dtcc_io/fields.py
dtcc_io/generic.py
dtcc_io/gridfield.py
dtcc_io/info.py
dtcc_io/landuse.py
dtcc_io/logging.py
dtcc_io/meshes.py
dtcc_io/pointcloud.py
dtcc_io/raster.py
dtcc_io/roadnetwork.py
dtcc_io/utils.py
dtcc_io/mesh_old/__init__.py
dtcc_io/mesh_old/mesh.py
dtcc_io/mesh_old/meshio_loaders.py
dtcc_io/mesh_old/pyassimp_loaders.py
dtcc_io/mesh_old/pygltflib_loaders.py
dtcc_io/mesh_old/utils.py
dtcc_io/scripts/__init__.py
dtcc_io/scripts/dtcc_info.py
dtcc_io-0.7.21.dist-info/LICENSE
dtcc_io-0.7.21.dist-info/METADATA
dtcc_io-0.7.21.dist-info/WHEEL
dtcc_io-0.7.21.dist-info/entry_points.txt
dtcc_io-0.7.21.dist-info/top_level.txt
dtcc_io-0.7.21.dist-info/RECORD
