Metadata-Version: 2.1
Name: dtcc-io
Version: 0.7.21
Summary: DTCC IO
Author-email: Anders Logg <logg@chalmers.se>, Vasilis Naserentin <vasilis.naserentin@chalmers.se>, Dag Wästberg <dwastberg@gmail.com>, George Spaias <gspaiasa@ece.auth.gr>, Jens Olsson <jens.olsson@chalmersindustriteknik.se>
Classifier: Intended Audience :: Science/Research
Classifier: Programming Language :: Python :: 3
Classifier: License :: OSI Approved :: MIT License
Requires-Python: >=3.10
License-File: LICENSE
Requires-Dist: protobuf <3.21.0,>=3.20.0
Requires-Dist: laspy[lazrs] <3.0.0,>=2.3.0
Requires-Dist: numpy <2.0.0,>=1.20.0
Requires-Dist: scipy <2.0.0,>=1.6.0
Requires-Dist: Fiona <2.0.0,>=1.8.0
Requires-Dist: rasterio <2.0.0,>=1.2.0
Requires-Dist: shapely <3.0.0,>=2.0.0
Requires-Dist: meshio <6.0.0,>=5.0.0
Requires-Dist: pyassimp
Requires-Dist: pygltflib
Requires-Dist: pyproj <4.0.0,>=3.1.0
Requires-Dist: pillow <10.0.0,>=9.0.0
Requires-Dist: rasterstats <1.0.0,>=0.19.0
Requires-Dist: dtcc-model >=0.7.21
Requires-Dist: dtcc-common >=0.7.21
Provides-Extra: test
Requires-Dist: pytest ; extra == 'test'
